{"stats":{"minecraft:killed_by":{"minecraft:player":5},"minecraft:used":{"minecraft:golden_apple":6,"minecraft:netherite_sword":29,"minecraft:bow":14},"minecraft:custom":{"minecraft:jump":132,"minecraft:time_since_rest":1747,"minecraft:damage_taken":1321,"minecraft:walk_one_cm":25283,"minecraft:damage_dealt":655,"minecraft:crouch_one_cm":133,"minecraft:leave_game":8,"minecraft:sprint_one_cm":8318,"minecraft:play_time":8577,"minecraft:time_since_death":1739,"minecraft:deaths":5,"minecraft:damage_absorbed":200,"minecraft:sneak_time":872,"minecraft:total_world_time":8577,"minecraft:damage_dealt_absorbed":88,"minecraft:fall_one_cm":4791,"minecraft:fly_one_cm":30726,"minecraft:player_kills":1}},"DataVersion":4082}