{"stats":{"minecraft:used":{"minecraft:respawn_anchor":98,"minecraft:golden_apple":10,"minecraft:netherite_sword":28,"minecraft:glowstone":36,"minecraft:end_crystal":239,"minecraft:netherite_pickaxe":94,"minecraft:ender_pearl":66,"minecraft:totem_of_undying":84,"minecraft:obsidian":211},"minecraft:mined":{"minecraft:fire":11,"minecraft:stone":83,"minecraft:obsidian":1},"minecraft:broken":{"minecraft:netherite_helmet":3},"minecraft:custom":{"minecraft:time_since_rest":179,"minecraft:damage_absorbed":5788,"minecraft:crouch_one_cm":1212,"minecraft:deaths":26,"minecraft:play_time":31724,"minecraft:sprint_one_cm":215174,"minecraft:walk_one_cm":89500,"minecraft:damage_taken":19183,"minecraft:sneak_time":855,"minecraft:jump":356,"minecraft:damage_dealt":247,"minecraft:leave_game":3,"minecraft:time_since_death":179,"minecraft:total_world_time":31724,"minecraft:damage_dealt_absorbed":6099,"minecraft:fall_one_cm":25670,"minecraft:fly_one_cm":59738}},"DataVersion":4189}