{"stats":{"minecraft:used":{"minecraft:golden_apple":2,"minecraft:respawn_anchor":2,"minecraft:glowstone":1,"minecraft:totem_of_undying":1},"minecraft:custom":{"minecraft:jump":30,"minecraft:time_since_rest":438,"minecraft:leave_game":1,"minecraft:deaths":1,"minecraft:damage_absorbed":138,"minecraft:sprint_one_cm":1468,"minecraft:play_time":1605,"minecraft:damage_taken":550,"minecraft:time_since_death":438,"minecraft:walk_one_cm":2650,"minecraft:total_world_time":1605,"minecraft:fall_one_cm":2534,"minecraft:fly_one_cm":6389}},"DataVersion":4189}