{"stats":{"minecraft:used":{"minecraft:respawn_anchor":4,"minecraft:golden_apple":64,"minecraft:netherite_sword":50,"minecraft:glowstone":24,"minecraft:mace":72,"minecraft:end_crystal":84,"minecraft:wind_charge":14,"minecraft:netherite_pickaxe":14,"minecraft:crossbow":4,"minecraft:ender_pearl":113,"minecraft:totem_of_undying":16,"minecraft:obsidian":353},"minecraft:mined":{"minecraft:short_grass":5,"minecraft:glowstone":1,"minecraft:dirt":2,"minecraft:iron_ore":1,"minecraft:fire":3,"minecraft:stone":1,"minecraft:andesite":2,"minecraft:obsidian":10},"minecraft:broken":{"minecraft:netherite_helmet":1},"minecraft:picked_up":{"minecraft:ender_pearl":1},"minecraft:custom":{"minecraft:time_since_rest":36,"minecraft:crouch_one_cm":12829,"minecraft:damage_absorbed":2462,"minecraft:play_time":48570,"minecraft:sprint_one_cm":115125,"minecraft:deaths":2,"minecraft:damage_taken":10970,"minecraft:walk_one_cm":85395,"minecraft:sneak_time":5872,"minecraft:walk_under_water_one_cm":1127,"minecraft:jump":1103,"minecraft:damage_dealt":1408,"minecraft:leave_game":3,"minecraft:walk_on_water_one_cm":6562,"minecraft:time_since_death":36,"minecraft:total_world_time":48570,"minecraft:damage_dealt_absorbed":1281,"minecraft:swim_one_cm":733,"minecraft:fall_one_cm":123556,"minecraft:fly_one_cm":98649}},"DataVersion":4189}