{"stats":{"minecraft:used":{"minecraft:netherite_sword":68,"minecraft:respawn_anchor":7,"minecraft:golden_apple":113,"minecraft:firework_rocket":144,"minecraft:mace":4,"minecraft:netherite_leggings":1,"minecraft:end_crystal":84,"minecraft:wind_charge":24,"minecraft:netherite_chestplate":27,"minecraft:netherite_pickaxe":1,"minecraft:elytra":37,"minecraft:pink_shulker_box":1,"minecraft:crossbow":6,"minecraft:netherite_helmet":1,"minecraft:ender_pearl":80,"minecraft:shield":4,"minecraft:ender_chest":2,"minecraft:white_shulker_box":2,"minecraft:splash_potion":6,"minecraft:totem_of_undying":28,"minecraft:obsidian":162},"minecraft:mined":{"minecraft:fire":5,"minecraft:white_shulker_box":1},"minecraft:broken":{"minecraft:netherite_helmet":1,"minecraft:netherite_boots":1},"minecraft:custom":{"minecraft:time_since_rest":2453,"minecraft:walk_one_cm":235135,"minecraft:damage_taken":22033,"minecraft:crouch_one_cm":11815,"minecraft:open_shulker_box":7,"minecraft:play_time":89055,"minecraft:sprint_one_cm":214626,"minecraft:open_enderchest":2,"minecraft:damage_absorbed":4568,"minecraft:deaths":20,"minecraft:damage_blocked_by_shield":60,"minecraft:sneak_time":3747,"minecraft:aviate_one_cm":913794,"minecraft:jump":1042,"minecraft:damage_dealt":571,"minecraft:leave_game":7,"minecraft:time_since_death":2453,"minecraft:total_world_time":89055,"minecraft:damage_dealt_absorbed":1609,"minecraft:fall_one_cm":29449,"minecraft:fly_one_cm":225008}},"DataVersion":4189}