{"stats":{"minecraft:used":{"minecraft:netherite_sword":22,"minecraft:golden_apple":14,"minecraft:respawn_anchor":15,"minecraft:glowstone":3,"minecraft:end_crystal":36,"minecraft:netherite_pickaxe":103,"minecraft:ender_pearl":7,"minecraft:totem_of_undying":17,"minecraft:obsidian":68},"minecraft:mined":{"minecraft:respawn_anchor":1,"minecraft:glowstone":2,"minecraft:stone":88,"minecraft:obsidian":8},"minecraft:custom":{"minecraft:time_since_rest":1,"minecraft:crouch_one_cm":3772,"minecraft:damage_absorbed":1564,"minecraft:deaths":13,"minecraft:play_time":16053,"minecraft:sprint_one_cm":27276,"minecraft:walk_one_cm":41170,"minecraft:damage_taken":7794,"minecraft:sneak_time":1798,"minecraft:jump":201,"minecraft:damage_dealt":173,"minecraft:leave_game":2,"minecraft:time_since_death":0,"minecraft:total_world_time":16053,"minecraft:damage_dealt_absorbed":636,"minecraft:fall_one_cm":27758,"minecraft:fly_one_cm":22328}},"DataVersion":4189}