{"stats":{"minecraft:broken":{"minecraft:netherite_helmet":2},"minecraft:used":{"minecraft:respawn_anchor":55,"minecraft:golden_apple":153,"minecraft:netherite_sword":86,"minecraft:glowstone":20,"minecraft:end_crystal":523,"minecraft:netherite_pickaxe":59,"minecraft:netherite_axe":3,"minecraft:crossbow":2,"minecraft:shield":36,"minecraft:ender_pearl":112,"minecraft:totem_of_undying":87,"minecraft:obsidian":237},"minecraft:custom":{"minecraft:time_since_rest":246,"minecraft:damage_absorbed":9295,"minecraft:crouch_one_cm":995,"minecraft:deaths":12,"minecraft:play_time":72750,"minecraft:sprint_one_cm":151730,"minecraft:walk_one_cm":110754,"minecraft:damage_taken":23211,"minecraft:damage_blocked_by_shield":13864,"minecraft:sneak_time":981,"minecraft:jump":915,"minecraft:damage_dealt":860,"minecraft:leave_game":2,"minecraft:time_since_death":246,"minecraft:total_world_time":72750,"minecraft:damage_dealt_absorbed":8086,"minecraft:fall_one_cm":63592,"minecraft:fly_one_cm":141484},"minecraft:mined":{"minecraft:mossy_cobblestone":1,"minecraft:fire":21,"minecraft:stone":56,"minecraft:obsidian":1}},"DataVersion":4189}